uralicNLP/__init__.py
uralicNLP/abrvs.json
uralicNLP/cg3.py
uralicNLP/dependency.py
uralicNLP/dictionary_backends.py
uralicNLP/download.py
uralicNLP/lang_codes.json
uralicNLP/llm.py
uralicNLP/neural_fst.py
uralicNLP/semantics.py
uralicNLP/semfi.py
uralicNLP/string_processing.py
uralicNLP/tokenizer.py
uralicNLP/translate.py
uralicNLP/ud_tools.py
uralicNLP/uralicApi.py
uralicNLP/foma/__init__.py
uralicNLP/foma/foma.py
uralicNLP/foma/six_1_11_0.py
uralicNLP-2.0.2.dist-info/LICENSE
uralicNLP-2.0.2.dist-info/METADATA
uralicNLP-2.0.2.dist-info/WHEEL
uralicNLP-2.0.2.dist-info/top_level.txt
uralicNLP-2.0.2.dist-info/RECORD
