Metadata-Version: 2.1
Name: uralicNLP
Version: 2.0.2
Summary: An NLP library for Uralic languages such as Finnish and Sami. Also supports Spanish, Arabic, Russian etc.
Home-page: https://github.com/mikahama/uralicNLP
Author: Mika Hämäläinen
Author-email: mika@flyforpoints.com
License: Apache-2.0 license
Project-URL: Bug Reports, https://github.com/mikahama/uralicNLP/issues
Project-URL: Wiki, https://github.com/mikahama/uralicNLP/wiki
Project-URL: Developer, https://mikakalevi.com/
Keywords: Uralic languages,NLP,morphology,hfst,omorfi,dictionary,lexicography
Classifier: Development Status :: 5 - Production/Stable
Classifier: Intended Audience :: Developers
Classifier: Topic :: Text Processing :: Linguistic
Classifier: Programming Language :: Python :: 3
License-File: LICENSE
Requires-Dist: requests
Requires-Dist: mikatools>=0.0.6
Requires-Dist: argparse
Requires-Dist: future>=0.18.2
Requires-Dist: tinydb
Requires-Dist: pyhfst
Requires-Dist: py-markdown-table
